bugbear-stubs/METADATA.toml
bugbear-stubs/__init__.pyi
bugbear-stubs/py.typed
types_flake8_bugbear-25.10.21.20251024.dist-info/licenses/LICENSE
types_flake8_bugbear-25.10.21.20251024.dist-info/METADATA
types_flake8_bugbear-25.10.21.20251024.dist-info/WHEEL
types_flake8_bugbear-25.10.21.20251024.dist-info/top_level.txt
types_flake8_bugbear-25.10.21.20251024.dist-info/RECORD
